carla_driving_simulator_client-2.0.38.dist-info/licenses/LICENSE
carla_simulator/__init__.py
carla_simulator/cli.py
carla_simulator/metrics.py
carla_simulator/control/controller.py
carla_simulator/control/interfaces.py
carla_simulator/control/keyboard.py
carla_simulator/control/vehicle_controller.py
carla_simulator/control/web_controller.py
carla_simulator/core/interfaces.py
carla_simulator/core/scenario_results_manager.py
carla_simulator/core/sensors.py
carla_simulator/core/simulation_application.py
carla_simulator/core/simulation_components.py
carla_simulator/core/simulation_manager.py
carla_simulator/core/simulation_runner.py
carla_simulator/core/vehicle.py
carla_simulator/core/vehicle_controller.py
carla_simulator/core/world_manager.py
carla_simulator/database/config.py
carla_simulator/database/db_manager.py
carla_simulator/database/init_db.py
carla_simulator/database/models.py
carla_simulator/database/setup.py
carla_simulator/scenarios/avoid_obstacle_scenario.py
carla_simulator/scenarios/base_scenario.py
carla_simulator/scenarios/emergency_brake_scenario.py
carla_simulator/scenarios/follow_route_scenario.py
carla_simulator/scenarios/scenario_registry.py
carla_simulator/scenarios/vehicle_cutting_scenario.py
carla_simulator/tests/__init__.py
carla_simulator/tests/conftest.py
carla_simulator/tests/test_carla_core.py
carla_simulator/tests/test_core.py
carla_simulator/tests/test_database_models.py
carla_simulator/tests/test_scenarios.py
carla_simulator/tests/test_utils.py
carla_simulator/utils/__init__.py
carla_simulator/utils/auth.py
carla_simulator/utils/config.py
carla_simulator/utils/default_config.py
carla_simulator/utils/logging.py
carla_simulator/utils/paths.py
carla_simulator/utils/settings.py
carla_simulator/utils/types.py
carla_simulator/visualization/__init__.py
carla_simulator/visualization/camera.py
carla_simulator/visualization/display_manager.py
carla_simulator/visualization/web_display_manager.py
web/backend/carla_pool.py
web/backend/main.py
web/backend/runner_registry.py
web/backend/tests/__init__.py
carla_driving_simulator_client-2.0.38.dist-info/METADATA
carla_driving_simulator_client-2.0.38.dist-info/WHEEL
carla_driving_simulator_client-2.0.38.dist-info/entry_points.txt
carla_driving_simulator_client-2.0.38.dist-info/top_level.txt
carla_driving_simulator_client-2.0.38.dist-info/RECORD
