Metadata-Version: 2.4
Name: carla-driving-simulator-client
Version: 2.0.38
Summary: A comprehensive CARLA client for autonomous driving simulation
Author-email: Akshay Chikhalkar <akshaychikhalkar15@gmail.com>
Maintainer-email: Akshay Chikhalkar <akshaychikhalkar15@gmail.com>
License: MIT
Project-URL: Homepage, https://github.com/akshaychikhalkar/carla-driving-simulator-client
Project-URL: Documentation, https://carla-driving-simulator-client.readthedocs.io/
Project-URL: Repository, https://github.com/akshaychikhalkar/carla-driving-simulator-client
Project-URL: Bug Tracker, https://github.com/akshaychikhalkar/carla-driving-simulator-client/issues
Keywords: carla,autonomous-driving,simulation,pygame,visualization,scenario-testing,vehicle-control
Classifier: Development Status :: 3 - Alpha
Classifier: Intended Audience :: Developers
Classifier: Intended Audience :: Science/Research
Classifier: License :: OSI Approved :: MIT License
Classifier: Programming Language :: Python :: 3
Classifier: Programming Language :: Python :: 3.11
Classifier: Topic :: Scientific/Engineering
Classifier: Topic :: Scientific/Engineering :: Artificial Intelligence
Classifier: Topic :: Software Development :: Libraries :: Python Modules
Classifier: Topic :: Software Development :: Testing
Classifier: Topic :: Games/Entertainment :: Simulation
Classifier: Operating System :: OS Independent
Classifier: Environment :: Console
Classifier: Environment :: Web Environment
Requires-Python: >=3.11
License-File: LICENSE
Requires-Dist: pygame>=2.0.0
Requires-Dist: numpy<2.0.0,>=1.19.0
Requires-Dist: matplotlib>=3.3.0
Requires-Dist: tabulate>=0.8.7
Requires-Dist: pyyaml>=5.4.0
Requires-Dist: psycopg2-binary>=2.9.9
Requires-Dist: SQLAlchemy>=2.0.0
Requires-Dist: alembic>=1.13.0
Provides-Extra: dev
Requires-Dist: pytest>=6.0.0; extra == "dev"
Requires-Dist: pytest-cov>=2.10.0; extra == "dev"
Requires-Dist: pytest-html>=3.2.0; extra == "dev"
Requires-Dist: black>=21.5b2; extra == "dev"
Requires-Dist: flake8>=3.9.0; extra == "dev"
Requires-Dist: mypy>=0.812; extra == "dev"
Provides-Extra: docs
Requires-Dist: sphinx>=4.0.0; extra == "docs"
Requires-Dist: sphinx-rtd-theme>=0.5.0; extra == "docs"
Requires-Dist: myst-parser>=0.15.0; extra == "docs"
Dynamic: license-file
